speechmlpipeline/__init__.py
speechmlpipeline/main_pipeline_local_function.py
speechmlpipeline/sample_run.py
speechmlpipeline/sample_run_existingllama2output.py
speechmlpipeline/AudioToTextTranscription/Whisper.py
speechmlpipeline/AudioToTextTranscription/Whispertimestamped.py
speechmlpipeline/AudioToTextTranscription/__init__.py
speechmlpipeline/DownloadModels/Download_Llama_Model.py
speechmlpipeline/DownloadModels/Download_Speechbrain_Model.py
speechmlpipeline/DownloadModels/Download_Whisper_Model.py
speechmlpipeline/DownloadModels/__init__.py
speechmlpipeline/DownloadModels/download_models_main_function.py
speechmlpipeline/EnsembleSpeakerChangeDetection/__init__.py
speechmlpipeline/EnsembleSpeakerChangeDetection/ensemble_detection.py
speechmlpipeline/Evaluation/__init__.py
speechmlpipeline/Evaluation/SpeakerChangeDetection/__init__.py
speechmlpipeline/Evaluation/SpeakerChangeDetection/examine_pyannote_metrics.py
speechmlpipeline/Evaluation/SpeakerChangeDetection/metrics_main_function.py
speechmlpipeline/Evaluation/SpeakerChangeDetection/metrics_main_function_revised.py
speechmlpipeline/Helpers/helpers.py
speechmlpipeline/PreprocessData/Run_VideoAudioPreprocessing.py
speechmlpipeline/PreprocessData/VideoAudioPreprocessing.py
speechmlpipeline/PreprocessData/__init__.py
speechmlpipeline/SpeakerChangeDetection/__init__.py
speechmlpipeline/SpeakerChangeDetection/speaker_change_detection_main_function.py
speechmlpipeline/SpeakerIdentification/__init__.py
speechmlpipeline/SpeakerIdentification/speaker_identification_main_function.py
speechmlpipeline-1.1.0.dist-info/LICENSE
speechmlpipeline-1.1.0.dist-info/METADATA
speechmlpipeline-1.1.0.dist-info/WHEEL
speechmlpipeline-1.1.0.dist-info/top_level.txt
speechmlpipeline-1.1.0.dist-info/RECORD
