Metadata-Version: 2.1
Name: speechmlpipeline
Version: 1.1.0
Summary: A package of speech machine learning pipeline to automatically get transcriptions with speaker labels from audio inputs
Author-email: "Junying (Alice) Fang" <jf3375@princeton.edu>
Project-URL: Homepage, https://github.com/princeton-ddss/SpeechMLPipeline
Classifier: Programming Language :: Python :: 3
Classifier: License :: OSI Approved :: MIT License
Classifier: Operating System :: OS Independent
Requires-Python: >=3.7
License-File: LICENSE
Requires-Dist: numpy
Provides-Extra: docs
Requires-Dist: myst-parser ; extra == 'docs'
Requires-Dist: sphinx ; extra == 'docs'
Requires-Dist: sphinx-rtd-theme ; extra == 'docs'
